clean_rst/__init__.py
clean_rst/__main__.py
clean_rst/main.py
clean_rst-0.1.4.dist-info/entry_points.txt
clean_rst-0.1.4.dist-info/WHEEL
clean_rst-0.1.4.dist-info/METADATA
clean_rst-0.1.4.dist-info/RECORD
