Metadata-Version: 2.1
Name: clean-rst
Version: 0.1.4
Summary: pre-commit to clean rst index files
Author: Bertrand Benjamin
Author-email: benjamin.bertrand@opytex.org
Requires-Python: >=3.10,<4.0
Classifier: Programming Language :: Python :: 3
Classifier: Programming Language :: Python :: 3.10
Requires-Dist: GitPython (>=3.1.27,<4.0.0)
Requires-Dist: click (>=8.1.3,<9.0.0)
Requires-Dist: restructuredtext-lint (>=1.4.0,<2.0.0)
